colearn/__init__.py
colearn/ml_interface.py
colearn/standalone_driver.py
colearn/training.py
colearn/utils/__init__.py
colearn/utils/data.py
colearn/utils/plot.py
colearn/utils/results.py
colearn_examples/grpc/mlifactory_grpc_mnist.py
colearn_examples/grpc/mnist_grpc.py
colearn_examples/grpc/run_grpc_demo.py
colearn_examples/ml_interface/keras_cifar.py
colearn_examples/ml_interface/keras_fraud.py
colearn_examples/ml_interface/keras_mnist.py
colearn_examples/ml_interface/keras_mnist_diffpriv.py
colearn_examples/ml_interface/keras_xray.py
colearn_examples/ml_interface/mli_fraud.py
colearn_examples/ml_interface/mli_random_forest_iris.py
colearn_examples/ml_interface/pytorch_cifar.py
colearn_examples/ml_interface/pytorch_covid.py
colearn_examples/ml_interface/pytorch_mnist.py
colearn_examples/ml_interface/pytorch_mnist_diffpriv.py
colearn_examples/ml_interface/pytorch_xray.py
colearn_examples/ml_interface/run_demo.py
colearn_examples/ml_interface/xgb_reg_boston.py
colearn_grpc/__init__.py
colearn_grpc/example_grpc_learner_client.py
colearn_grpc/example_mli_factory.py
colearn_grpc/factory_registry.py
colearn_grpc/grpc_learner_server.py
colearn_grpc/grpc_server.py
colearn_grpc/logging.py
colearn_grpc/mli_factory_interface.py
colearn_grpc/test_example_mli_factory.py
colearn_grpc/test_grpc_utils.py
colearn_grpc/utils.py
colearn_grpc/proto/generated/interface_pb2.py
colearn_grpc/proto/generated/interface_pb2_grpc.py
colearn_grpc/scripts/probe_grpc_server.py
colearn_grpc/scripts/run_grpc_server.py
colearn_grpc/scripts/run_n_grpc_servers.py
colearn_keras/__init__.py
colearn_keras/keras_cifar10.py
colearn_keras/keras_learner.py
colearn_keras/keras_mnist.py
colearn_keras/test_keras_learner.py
colearn_keras/utils.py
colearn_other/__init__.py
colearn_other/demo_utils.py
colearn_other/fraud_dataset.py
colearn_pytorch/__init__.py
colearn_pytorch/pytorch_covid_xray.py
colearn_pytorch/pytorch_learner.py
colearn_pytorch/pytorch_xray.py
colearn_pytorch/test_pytorch_learner.py
colearn-0.2.8.dist-info/LICENSE
colearn-0.2.8.dist-info/METADATA
colearn-0.2.8.dist-info/WHEEL
colearn-0.2.8.dist-info/top_level.txt
colearn-0.2.8.dist-info/RECORD
