Metadata-Version: 2.1
Name: colearn
Version: 0.2.8
Summary: The Standalone Fetch AI Collective Learning Framework
Home-page: https://github.com/fetchai/colearn
Author: Fetch AI
Author-email: developer@fetch.ai
License: UNKNOWN
Platform: UNKNOWN
Classifier: Operating System :: OS Independent
Requires-Python: >=3.7, <3.9
Requires-Dist: google-cloud-storage (<1.44,>=1.35)
Requires-Dist: matplotlib (<3.6,>=3.3)
Requires-Dist: numpy (~=1.16.0)
Requires-Dist: pydantic (<1.10,>=1.7)
Provides-Extra: all
Requires-Dist: click ; extra == 'all'
Requires-Dist: tensorflow-privacy (<0.8,>=0.5) ; extra == 'all'
Requires-Dist: grpcio (<1.43,>=1.35) ; extra == 'all'
Requires-Dist: opacus (<1.1,>=1.0.0) ; extra == 'all'
Requires-Dist: Pillow (<9.1.0,>=8.0.1) ; extra == 'all'
Requires-Dist: torchsummary (~=1.5.0) ; extra == 'all'
Requires-Dist: scikit-learn (<1.1,>=0.23) ; extra == 'all'
Requires-Dist: scipy (<1.8,>=1.5) ; extra == 'all'
Requires-Dist: grpcio-tools (<1.43,>=1.35) ; extra == 'all'
Requires-Dist: tensorflow-datasets (<4.5,>=4.2) ; extra == 'all'
Requires-Dist: torchvision (<0.12,>=0.8) ; extra == 'all'
Requires-Dist: pandas (~=1.1.0) ; extra == 'all'
Requires-Dist: torch (<1.11,>=1.7) ; extra == 'all'
Requires-Dist: tensorflow (<2.8,>=2.2) ; extra == 'all'
Requires-Dist: prometheus-client (==0.12.0) ; extra == 'all'
Requires-Dist: xgboost ; extra == 'all'
Provides-Extra: docs
Requires-Dist: mkdocs ; extra == 'docs'
Requires-Dist: mkdocs-macros-plugin ; extra == 'docs'
Requires-Dist: mkdocs-material ; extra == 'docs'
Requires-Dist: mkdocs-material-extensions ; extra == 'docs'
Requires-Dist: markdown-include ; extra == 'docs'
Provides-Extra: grpc
Requires-Dist: grpcio (<1.43,>=1.35) ; extra == 'grpc'
Requires-Dist: grpcio-tools (<1.43,>=1.35) ; extra == 'grpc'
Requires-Dist: prometheus-client (==0.12.0) ; extra == 'grpc'
Requires-Dist: click ; extra == 'grpc'
Provides-Extra: keras
Requires-Dist: tensorflow (<2.8,>=2.2) ; extra == 'keras'
Requires-Dist: tensorflow-datasets (<4.5,>=4.2) ; extra == 'keras'
Requires-Dist: tensorflow-privacy (<0.8,>=0.5) ; extra == 'keras'
Provides-Extra: other
Requires-Dist: pandas (~=1.1.0) ; extra == 'other'
Requires-Dist: scikit-learn (<1.1,>=0.23) ; extra == 'other'
Provides-Extra: pytorch
Requires-Dist: opacus (<1.1,>=1.0.0) ; extra == 'pytorch'
Requires-Dist: Pillow (<9.1.0,>=8.0.1) ; extra == 'pytorch'
Requires-Dist: scikit-learn (<1.1,>=0.23) ; extra == 'pytorch'
Requires-Dist: scipy (<1.8,>=1.5) ; extra == 'pytorch'
Requires-Dist: torch (<1.11,>=1.7) ; extra == 'pytorch'
Requires-Dist: torchsummary (~=1.5.0) ; extra == 'pytorch'
Requires-Dist: torchvision (<0.12,>=0.8) ; extra == 'pytorch'
